yol/__init__.py
yol/server.py
yol/trace_logic.py
yol/version.py
yol/version_check.py
yol/trace_display/package-lock.json
yol/trace_display/package.json
yol/trace_display/build/asset-manifest.json
yol/trace_display/build/favicon.ico
yol/trace_display/build/index.html
yol/trace_display/build/logo192.png
yol/trace_display/build/logo512.png
yol/trace_display/build/manifest.json
yol/trace_display/build/precache-manifest.14ddd0c669e7569498590032e461b7d4.js
yol/trace_display/build/robots.txt
yol/trace_display/build/service-worker.js
yol/trace_display/build/static/css/main.95ce86eb.chunk.css
yol/trace_display/build/static/css/main.95ce86eb.chunk.css.map
yol/trace_display/build/static/js/2.368d16db.chunk.js
yol/trace_display/build/static/js/2.368d16db.chunk.js.LICENSE.txt
yol/trace_display/build/static/js/2.368d16db.chunk.js.map
yol/trace_display/build/static/js/main.1cb23814.chunk.js
yol/trace_display/build/static/js/main.1cb23814.chunk.js.map
yol/trace_display/build/static/js/runtime-main.7180217b.js
yol/trace_display/build/static/js/runtime-main.7180217b.js.map
yol/trace_display/public/favicon.ico
yol/trace_display/public/index.html
yol/trace_display/public/logo192.png
yol/trace_display/public/logo512.png
yol/trace_display/public/manifest.json
yol/trace_display/public/robots.txt
yol/trace_display/src/.DS_Store
yol/trace_display/src/App.tsx
yol/trace_display/src/NeuralBridge.css
yol/trace_display/src/index.css
yol/trace_display/src/index.js
yol/trace_display/src/logo.svg
yol/trace_display/src/react-app-env.d.ts
yol/trace_display/src/components/CodeWindow.css
yol/trace_display/src/components/CodeWindow.tsx
yol/trace_display/src/components/Footer.css
yol/trace_display/src/components/Footer.tsx
yol/trace_display/src/components/Header.css
yol/trace_display/src/components/Header.tsx
yol/trace_display/src/components/InputOutputButton.css
yol/trace_display/src/components/InputOutputButton.tsx
yol/trace_display/src/components/InputOutputWindow.css
yol-0.1.5.dist-info/LICENSE
yol-0.1.5.dist-info/METADATA
yol-0.1.5.dist-info/WHEEL
yol-0.1.5.dist-info/top_level.txt
yol-0.1.5.dist-info/RECORD
